email_signals/__init__.py
email_signals/admin.py
email_signals/apps.py
email_signals/constraint_checker.py
email_signals/constraint_methods.py
email_signals/emailer.py
email_signals/forms.py
email_signals/models.py
email_signals/registry.py
email_signals/signals.py
email_signals/urls.py
email_signals/utils.py
email_signals/views.py
email_signals/migrations/0001_initial.py
email_signals/migrations/0002_auto_20211203_1357.py
email_signals/migrations/0003_auto_20211204_0211.py
email_signals/migrations/0004_alter_signal_html_email.py
email_signals/migrations/0005_auto_20211204_1258.py
email_signals/migrations/0006_auto_20211204_1335.py
email_signals/migrations/0007_alter_signal_mailing_list.py
email_signals/migrations/__init__.py
email_signals/templates/email_signals/admin/email_signals/signal/change_form.html
email_signals/templatetags/__init__.py
email_signals/templatetags/email_signal_tags.py
email_signals/tests/__init__.py
email_signals/tests/models.py
email_signals/tests/test_constraint_checker.py
email_signals/tests/test_constraint_methods.py
email_signals/tests/test_emailer.py
email_signals/tests/test_forms.py
email_signals/tests/test_models.py
email_signals/tests/test_registry.py
email_signals/tests/test_signals.py
email_signals/tests/test_utils.py
email_signals/tests/testcase.py
django_email_signals-2.0.0.dist-info/LICENSE
django_email_signals-2.0.0.dist-info/METADATA
django_email_signals-2.0.0.dist-info/WHEEL
django_email_signals-2.0.0.dist-info/top_level.txt
django_email_signals-2.0.0.dist-info/RECORD
