Metadata-Version: 2.1
Name: django-email-signals
Version: 2.0.0
Summary: A Django app that allows users to dynamically send emails whenever there are some changes on some tables.
Home-page: https://github.com/Salaah01/django-email-signals
Author: Salaah Amin
License: MIT
Platform: UNKNOWN
Classifier: Intended Audience :: Developers
Classifier: Operating System :: OS Independent
Classifier: Programming Language :: Python
Classifier: Programming Language :: Python :: 3
Classifier: Programming Language :: Python :: 3 :: Only
Classifier: Programming Language :: Python :: 3.8
Classifier: Programming Language :: Python :: 3.9
Classifier: Programming Language :: Python :: 3.10
Classifier: Topic :: Software Development :: Libraries :: Python Modules
Requires-Python: >=3.8
License-File: LICENSE
